shared_code/__init__.py
shared_code/edwh/__init__.py
shared_code/edwh/core/__init__.py
shared_code/edwh/core/data_model.py
shared_code/edwh/core/migrations.py
shared_code/edwh/core/tags.py
shared_code/edwh/core/applog/__init__.py
shared_code/edwh/core/applog/asink.py
shared_code/edwh/core/applog/celerysink.py
shared_code/edwh/core/applog/diskcachesink.py
shared_code/edwh/core/applog/signalemitter.py
shared_code/edwh/core/applog/sink.py
shared_code/edwh/core/applog/tasks.py
shared_code/edwh/core/backend/__init__.py
shared_code/edwh/core/backend/engine.py
shared_code/edwh/core/backend/ntfy_sh.py
shared_code/edwh/core/backend/opengraph.py
shared_code/edwh/core/backend/support.py
shared_code/edwh/core/backend/tasks.py
shared_code/edwh/core/jwt_tools/__init__.py
shared_code/edwh/core/jwt_tools/jwt_py4web.py
shared_code/edwh/core/jwt_tools/jwt_web2py.py
shared_code/edwh/core/jwt_tools/shared.py
shared_code/edwh/core/pgcache/__init__.py
shared_code/edwh/core/pgcache/clean.py
shared_code/edwh/core/pgcache/define_models.py
shared_code/edwh/core/sync/__init__.py
shared_code/edwh/core/web2py_tools/__init__.py
ontwikkelstraat-1.19.1.dist-info/METADATA
ontwikkelstraat-1.19.1.dist-info/WHEEL
ontwikkelstraat-1.19.1.dist-info/licenses/LICENSE.txt
ontwikkelstraat-1.19.1.dist-info/RECORD
